easyCAL2.py
easycal2-1.2.0.dist-info/LICENSE
easycal2-1.2.0.dist-info/METADATA
easycal2-1.2.0.dist-info/WHEEL
easycal2-1.2.0.dist-info/top_level.txt
easycal2-1.2.0.dist-info/RECORD
