Metadata-Version: 2.1
Name: easyCAL2
Version: 1.2.0
Summary: A package for calculate Math problem contain easy calculation and easy linear algebra problem, in the future author will add functions to solve easy geometry problems.
Author-email: AndyJinXi <appleking0@icloud.com>
License: Apache 2.0
Project-URL: home, https://gitee.com/JXX_CODE/easycalculate
Classifier: Intended Audience :: Developers
Classifier: Operating System :: OS Independent
Classifier: Programming Language :: Python :: 3
Requires-Python: >=3.7
License-File: LICENSE
Requires-Dist: numpy==1.24.4
